up2superbed.py
up2superbed-0.1.0.dist-info/METADATA
up2superbed-0.1.0.dist-info/WHEEL
up2superbed-0.1.0.dist-info/top_level.txt
up2superbed-0.1.0.dist-info/RECORD
