Metadata-Version: 2.1
Name: up2superbed
Version: 0.1.0
Summary: Save uploaded pictures in superbed.cn
Home-page: https://github.com/staugur/picbed-up2superbed
Author: staugur
Author-email: staugur@saintic.com
License: BSD 3-Clause
Platform: UNKNOWN
Requires-Dist: requests
